accounts/__init__.py
accounts/admin.py
accounts/apps.py
accounts/authentication.py
accounts/backends.py
accounts/ipc.py
accounts/migrations/0001_initial.py
accounts/migrations/__init__.py
accounts/migrations/rename_groups.py
accounts/models.py
accounts/settings.py
accounts/urls.py
accounts/views.py
analytics/README.md
analytics/__init__.py
analytics/analytics.py
analytics/apps.py
analytics/entries.py
identity/__init__.py
identity/apps.py
identity/identity.py
identity/permissions.py
django_labs_accounts-1.0.6.dist-info/METADATA
django_labs_accounts-1.0.6.dist-info/WHEEL
django_labs_accounts-1.0.6.dist-info/licenses/LICENSE
django_labs_accounts-1.0.6.dist-info/RECORD
