Metadata-Version: 2.4
Name: django-labs-accounts
Version: 1.0.6
Summary: Reusable Django app for Penn Labs accounts
License: MIT
License-File: LICENSE
Author: Penn Labs
Author-email: contact@pennlabs.org
Requires-Python: >=3.11,<4.0
Classifier: License :: OSI Approved :: MIT License
Classifier: Programming Language :: Python :: 3
Classifier: Programming Language :: Python :: 3.11
Classifier: Programming Language :: Python :: 3.12
Classifier: Programming Language :: Python :: 3.13
Classifier: Programming Language :: Python :: 3.14
Requires-Dist: Django (>=5.0.2,<6.0.0)
Requires-Dist: djangorestframework (>=3.14.0,<4.0.0)
Requires-Dist: jwcrypto (>=1.4.2,<2.0.0)
Requires-Dist: requests (>=2.0.0,<3.0.0)
Requires-Dist: requests-oauthlib (>=1.3.1,<2.0.0)
Requires-Dist: six (>=1.16.0,<2.0.0)
Project-URL: Homepage, https://github.com/pennlabs/django-labs-accounts
Project-URL: Repository, https://github.com/pennlabs/django-labs-accounts
